npids/__init__.py
npids/builder.py
npids/lookup.py
npids/utils.py
npids/codecs/__init__.py
npids/codecs/fwd_fixedbytes.py
npids/codecs/fwd_hexdigest.py
npids/codecs/fwd_intsequence.py
npids/codecs/fwd_intsequencepad.py
npids/codecs/fwd_intstored.py
npids/codecs/fwd_uuid.py
npids/codecs/inv_hash.py
npids/codecs/inv_intsequence.py
npids/codecs/inv_intsequencemulti.py
npids/codecs/inv_intstored.py
test/__init__.py
test/test_bugs.py
test/test_datasets.py
npids-0.1.2.dist-info/LICENSE
npids-0.1.2.dist-info/METADATA
npids-0.1.2.dist-info/WHEEL
npids-0.1.2.dist-info/top_level.txt
npids-0.1.2.dist-info/RECORD
