Metadata-Version: 2.2
Name: npids
Version: 0.1.2
Author: Sean MacAvaney
Author-email: sean.macavaney@glasgow.ac.uk
Requires-Python: >=3.6
License-File: LICENSE
Dynamic: author
Dynamic: author-email
Dynamic: description
Dynamic: description-content-type
Dynamic: requires-python
